Workbook

Sheet Base
A1: Ref METRO | B1: MGB | C1: Libellé Article | D1: Secteur Activité | E1: Groupe Article | F1: Sous-groupe Article | G1: Format | H1: Déploiement National / Local | I1: FAMILLE | J1: Longueur | K1: Largeur | L1: Hauteur | M1: Volume | N1: Conditionnement Vente | O1: Conditionnement fournisseur | P1: Vendu au poids | Q1: CELLULE
A2: 242267 | B2: 835280001001 | C2: * MAYONAIS 970ML CALIFORN | D2: 51 - POLE SALE | E2: 396 - SAUCES FROIDES | F2: 20 - MAYONNAISE | G2: 30 - MAYONNAISE > 70% D HUILE | H2: DF1 | I2: SEC | J2: 8.3 | K2: 8.3 | L2: 28.5 | M2: 1963.365 | N2: 1 | O2: 6
A3: 307663 | B3: 895622001001 | C3: *AIL SEMOULE 1KG ARO | D3: 51 - POLE SALE | E3: 394 - ASSAISONNEMENTS | F3: 39420 - HERBES | G3: 3942045 - AIL | I3: SEC | N3: 1 | O3: 6 | P3: FALSE
A4: 247707 | B4: 840682001001 | C4: *CACAHUET GRILL 1,5KG MENG | D4: 52 - POLE SUCREE | E4: 401 - SNACKS SALES | F4: 10 - GRAINES | G4: 20 - CACAHUETES SALEES | H4: DF1 | I4: SEC | J4: 12 | K4: 8 | L4: 25 | M4: 2400 | N4: 1 | O4: 7 | P4: FALSE
A5: 247859 | B5: 840838001001 | C5: *CACAHUETE SALE 1,5KG MC | D5: 52 - POLE SUCREE | E5: 401 - SNACKS SALES | F5: 10 - GRAINES | G5: 20 - CACAHUETES SALEES | H5: DF1 | I5: TOP | J5: 22.5 | K5: 6 | L5: 33.5 | M5: 4522.5 | N5: 1 | O5: 6 | P5: FALSE
A6: 247770 | B6: 840753001001 | C6: *CHOC MILKA LAIT TB 100GX5 | D6: 52 - POLE SUCREE | E6: 402 - CHOCOLAT | F6: 10 - TABLETTES | G6: 20 - LAIT | H6: DF1 | I6: SEC | J6: 4 | K6: 8 | L6: 16 | M6: 512 | N6: 1 | O6: 30 | P6: FALSE
A7: 307677 | B7: 895635001001 | C7: *CUMIN MOULU 1KG ARO | D7: 51 - POLE SALE | E7: 394 - ASSAISONNEMENTS | F7: 30 - EPICES | G7: 11 - CUMIN | H7: DF1 | I7: SEC | N7: 1 | O7: 6 | P7: FALSE
A8: 12793 | B8: 212791001001 | C8: *ESCO SEL FIN SAC 25KG | D8: 51 - POLE SALE | E8: 394 - ASSAISONNEMENTS | F8: 10 - SEL | G8: 20 - SEL DE CUISINE | H8: DF1 | I8: SEC LOURD | J8: 34 | K8: 56 | L8: 12 | M8: 22848 | N8: 1 | O8: 1 | P8: FALSE
A9: 242188 | B9: 835170001002 | C9: *FARINE BLE T 55 1KG ARO | D9: 51 - POLE SALE | E9: 397 - FARINES | F9: 10 - FARINE DE BLE | G9: 05 - BLE TENDRE < 1KG | H9: DF1 | I9: SEC | J9: 39 | K9: 22 | L9: 17 | M9: 14586 | N9: 10 | O9: 10 | P9: FALSE
A10: 242203 | B10: 835185001002 | C10: *FARINE BLE T45 1KG ROC | D10: 51 - POLE SALE | E10: 397 - FARINES | F10: 10 - FARINE DE BLE | G10: 05 - BLE TENDRE < 1KG | H10: DF1 | I10: SEC | J10: 39 | K10: 22 | L10: 17 | M10: 14586 | N10: 10 | O10: 10 | P10: FALSE
A11: 242274 | B11: 835289001001 | C11: *KETCHUP 950ML CALIFORNIA | D11: 51 - POLE SALE | E11: 396 - SAUCES FROIDES | F11: 30 - KETCHUP | G11: 10 - KETCHUP | H11: DF1 | I11: SEC | J11: 8.3 | K11: 8.3 | L11: 28.5 | M11: 1963.365 | N11: 1 | O11: 6 | P11: FALSE
A12: 57605 | B12: 678011001001 | C12: *MC BOLETS ET CEPES 500GR | D12: 51 - POLE SALE | E12: 395 - CONDIMENTS SECHES | F12: 10 - CHAMPIGNONS SECS | G12: 30 - MELANGE DE CHAMPIGNONG | H12: DF1 | I12: SEC | J12: 13.4 | K12: 13.4 | L12: 24.3 | M12: 4363.308 | N12: 1 | O12: 6 | P12: FALSE
A13: 242281 | B13: 835300001001 | C13: *MC BP FARINE PATIS T45 10KG | D13: 51 - POLE SALE | E13: 397 - FARINES | F13: 40 - SPECIALE | G13: 40 - FARINE PATISSERIE | H13: DF1 | I13: SEC LOURD | J13: 15 | K13: 25 | L13: 44 | M13: 16500 | N13: 1 | O13: 1 | P13: FALSE
A14: 275539 | B14: 866457001001 | C14: *MC CEPES EXTRA TUBO 500G | D14: 51 - POLE SALE | E14: 395 - CONDIMENTS SECHES | F14: 10 - CHAMPIGNONS SECS | G14: 20 - BOLETUS | H14: DF1 | I14: SEC | J14: 13.5 | K14: 14 | L14: 24 | M14: 4536 | N14: 1 | O14: 6 | P14: FALSE
A15: 106008 | B15: 299847001001 | C15: *MC CONFIT CANARD 12 CUISS5/1 | D15: 51 - POLE SALE | E15: 369 - PLATS CUISINES EN CONSERVE | F15: 20 - VIANDES PREPAREES EN CONSERVE | G15: 10 - CONFIT | H15: DF1 | I15: SEC | J15: 15.3 | K15: 15.3 | L15: 24.6 | M15: 5758.614 | N15: 1 | O15: 2 | P15: FALSE
A16: 172362 | B16: 170153001001 | C16: *MC CONFIT GESIERS CANARD 4/4 | D16: 51 - POLE SALE | E16: 369 - PLATS CUISINES EN CONSERVE | F16: 20 - VIANDES PREPAREES EN CONSERVE | G16: 15 - GESIER | H16: DF1 | I16: SEC | J16: 9.9 | K16: 9.9 | L16: 11.8 | M16: 1156.518 | N16: 1 | O16: 6 | P16: FALSE
A17: 5116 | B17: 205114001001 | C17: *MC ESC. LUCO 4/4 12DZ MOYEN | D17: 51 - POLE SALE | E17: 368 - CONSERVE VIANDES/SAUCISSES | F17: 10 - VIANDE EN CONSERVE | G17: 50 - ESCARGOTS MEDIUM | H17: DF1 | I17: SEC | J17: 10 | K17: 10 | L17: 11.8 | M17: 1180 | N17: 1 | O17: 6 | P17: FALSE
A18: 5025 | B18: 205023001001 | C18: *MC ESC. POMA 4/4 10DZ B.GROS | D18: 51 - POLE SALE | E18: 368 - CONSERVE VIANDES/SAUCISSES | F18: 10 - VIANDE EN CONSERVE | G18: 55 - ESCARGOTS LARGE | H18: DF1 | I18: SEC | J18: 10 | K18: 10 | L18: 11.8 | M18: 1180 | N18: 1 | O18: 6 | P18: FALSE
A19: 5043 | B19: 205041001001 | C19: *MC ESC. POMA 4/4 12DZ MOYEN | D19: 51 - POLE SALE | E19: 368 - CONSERVE VIANDES/SAUCISSES | F19: 10 - VIANDE EN CONSERVE | G19: 50 - ESCARGOTS MEDIUM | H19: DF1 | I19: SEC | J19: 10 | K19: 10 | L19: 11.8 | M19: 1180 | N19: 1 | O19: 6
A20: 242279 | B20: 835297001001 | C20: *MC FARINE PANIF. T65 25KG | D20: 51 - POLE SALE | E20: 397 - FARINES | F20: 40 - SPECIALE | G20: 30 - FARINE BOULANGERIE | H20: DF1 | I20: SEC LOURD | J20: 35 | K20: 16 | L20: 70 | M20: 39200 | N20: 1 | O20: 1 | P20: FALSE
A21: 242175 | B21: 835154001002 | C21: *MC FARINE SARASIN 1KG | D21: 51 - POLE SALE | E21: 397 - FARINES | F21: 10 - FARINE DE BLE | G21: 55 - SARRASIN < 1KG | H21: DF1 | I21: SEC | J21: 40.1 | K21: 22.4 | L21: 16 | M21: 14371.84 | N21: 10 | O21: 10 | P21: FALSE
A22: 242282 | B22: 835301001001 | C22: *MC FARINE TTUSAG T55 10KG | D22: 51 - POLE SALE | E22: 397 - FARINES | F22: 10 - FARINE DE BLE | G22: 10 - BLE TENDRE > 1KG | H22: DF1 | I22: SEC LOURD | J22: 1.5 | K22: 2.4 | L22: 4.1 | M22: 14.76 | N22: 1 | O22: 1 | P22: FALSE
A23: 273564 | B23: 864458001001 | C23: *MC GARNITURE FOREST TUBO500G | D23: 51 - POLE SALE | E23: 395 - CONDIMENTS SECHES | F23: 10 - CHAMPIGNONS SECS | G23: 30 - MELANGE DE CHAMPIGNONG | H23: DF1 | I23: SEC | J23: 13.5 | K23: 14 | L23: 24 | M23: 4536 | N23: 1 | O23: 6 | P23: FALSE
A24: 172364 | B24: 170155001001 | C24: *MC GRAISSE DE CANARD 5/1 | D24: 51 - POLE SALE | E24: 369 - PLATS CUISINES EN CONSERVE | F24: 20 - VIANDES PREPAREES EN CONSERVE | G24: 25 - GRAISSE | H24: DF1 | I24: SEC | J24: 15.4 | K24: 15.4 | L24: 24.5 | M24: 5810.42 | N24: 1 | O24: 3 | P24: FALSE
A25: 175959 | B25: 173020001001 | C25: *MC MEL MEXICAIN POT 500GR | D25: 51 - POLE SALE | E25: 394 - ASSAISONNEMENTS | F25: 30 - EPICES | G25: 58 - MELANGE EPICES POUR VIANDE | H25: DF1 | I25: SEC | J25: 8.5 | K25: 8.5 | L25: 20 | M25: 1445 | N25: 1 | O25: 4 | P25: FALSE
A26: 63729 | B26: 635219001001 | C26: *MC MINI MORILLE SAUV TUBO500G | D26: 51 - POLE SALE | E26: 395 - CONDIMENTS SECHES | F26: 10 - CHAMPIGNONS SECS | G26: 60 - MORILLES | H26: DF1 | I26: SEC | N26: 1 | O26: 6 | P26: FALSE
A27: 212244 | B27: 806427001001 | C27: *MC MORILLE EXTRA SAU TUBO400G | D27: 51 - POLE SALE | E27: 395 - CONDIMENTS SECHES | F27: 10 - CHAMPIGNONS SECS | G27: 60 - MORILLES | H27: DF1 | I27: SEC | J27: 13.4 | K27: 13.4 | L27: 24.3 | M27: 4363.308 | N27: 1 | O27: 6 | P27: FALSE
A28: 4808 | B28: 685257001001 | C28: *MC MORILLE SAU JUMBO TUBO200G | D28: 51 - POLE SALE | E28: 395 - CONDIMENTS SECHES | F28: 10 - CHAMPIGNONS SECS | G28: 60 - MORILLES | H28: DF1 | I28: SEC | J28: 12 | K28: 12 | L28: 16 | M28: 2304 | N28: 1 | O28: 6 | P28: FALSE
A29: 212245 | B29: 806428001001 | C29: *MC MORILLE SAU SPECI TUBO400G | D29: 51 - POLE SALE | E29: 395 - CONDIMENTS SECHES | F29: 10 - CHAMPIGNONS SECS | G29: 60 - MORILLES | H29: DF1 | I29: SEC | J29: 13.4 | K29: 13.4 | L29: 24.3 | M29: 4363.308 | N29: 1 | O29: 6 | P29: FALSE
A30: 296912 | B30: 886101001001 | C30: *MC MORILLE TRAITEUR 400G | D30: 51 - POLE SALE | E30: 395 - CONDIMENTS SECHES | F30: 10 - CHAMPIGNONS SECS | G30: 60 - MORILLES | H30: DF1 | I30: SEC | N30: 1 | O30: 6 | P30: FALSE
A31: 40244 | B31: 676343001001 | C31: *MC QUEU MORILLE SAU TUBO500G | D31: 51 - POLE SALE | E31: 395 - CONDIMENTS SECHES | F31: 10 - CHAMPIGNONS SECS | G31: 60 - MORILLES | H31: DF1 | I31: SEC | J31: 13.4 | K31: 13.4 | L31: 24.3 | M31: 4363.308 | N31: 1 | O31: 6
A32: 307664 | B32: 895623001001 | C32: *ORIGAN ENTIER 500G ARO | D32: 51 - POLE SALE | E32: 394 - ASSAISONNEMENTS | F32: 20 - HERBES | G32: 60 - ORIGAN | H32: DF1 | I32: SEC | N32: 1 | O32: 10 | P32: FALSE
A33: 241654 | B33: 835513001001 | C33: *SEMOUL BLE DUR EXTRA FINE 5K | D33: 51 - POLE SALE | E33: 387 - GRAIN | F33: 10 - GRAINS/CEREALES | G33: 35 - GRAIN/BLE | H33: DF1 | I33: TOP | J33: 8 | K33: 17 | L33: 37 | M33: 5032 | N33: 1 | O33: 1 | P33: FALSE
A34: 241660 | B34: 835519001001 | C34: *SEMOUL BLE DUR MOYEN 5KG REN | D34: 51 - POLE SALE | E34: 387 - GRAIN | F34: 10 - GRAINS/CEREALES | G34: 35 - GRAIN/BLE | H34: DF1 | I34: SEC LOURD | J34: 8 | K34: 17 | L34: 37 | M34: 5032 | N34: 1 | O34: 1 | P34: FALSE
A35: 241658 | B35: 835517001001 | C35: *SEMOUL BLE EXTRA FIN 25KG | D35: 51 - POLE SALE | E35: 387 - GRAIN | F35: 10 - GRAINS/CEREALES | G35: 35 - GRAIN/BLE | H35: DF1 | I35: SEC LOURD | J35: 17 | K35: 38 | L35: 58 | M35: 37468 | N35: 1 | O35: 1 | P35: FALSE
A36: 241653 | B36: 835512001001 | C36: *SEMOUL BLE FIN 5KG RENARD | D36: 51 - POLE SALE | E36: 387 - GRAIN | F36: 10 - GRAINS/CEREALES | G36: 35 - GRAIN/BLE | H36: DF5 | I36: SEC LOURD | J36: 7 | K36: 18 | L36: 42 | M36: 5292 | N36: 1 | O36: 1 | P36: FALSE
A37: 241663 | B37: 835522001001 | C37: *SEMOUL PATES FRAICHE SAC 5K | D37: 51 - POLE SALE | E37: 397 - FARINES | F37: 40 - SPECIALE | G37: 20 - FARINE PATE | H37: DF1 | I37: SEC | J37: 11 | K37: 21 | L37: 40 | M37: 9240 | N37: 1 | O37: 1
A38: 71444 | B38: 71444001002 | C38: *SOLE 300/400 X6 P/ANE.SOLEA VULGARIS | D38: 61 - MAREE | E38: 342 - POISSONS DE MER ENTIERS | F38: 34209 - ATLANTIQUE NORD EST 27 | G38: 3420982 - SOLE | I38: Marée | N38: 1 | O38: 6 | P38: TRUE
A39: 247776 | B39: 840759001001 | C39: *SUCRE CRISTAL N2 BS SAC 25KG | D39: 52 - POLE SUCREE | E39: 382 - SUCRE ET EDULCORANT | F39: 10 - SUCRE BLANC | G39: 60 - SUCRE EN POUDRE > 1KG | H39: DF1 | I39: SEC LOURD | J39: 76 | K39: 38 | L39: 11.5 | M39: 33212 | N39: 1 | O39: 1 | P39: FALSE
A40: 247886 | B40: 840894001001 | C40: *SUCRE ENV AMBRE/BLANC 2,5KG | D40: 52 - POLE SUCREE | E40: 382 - SUCRE ET EDULCORANT | F40: 30 - SUCRE BRUN | G40: 10 - BRUN PORTION CUBES | H40: DF1 | I40: SEC | J40: 20 | K40: 20 | L40: 29 | M40: 11600 | N40: 1 | O40: 4 | P40: FALSE
A41: 247804 | B41: 840785001001 | C41: *SUCRE GLACE AMYLACE SAC 10KG | D41: 52 - POLE SUCREE | E41: 382 - SUCRE ET EDULCORANT | F41: 50 - BAKING/COOKING SUGAR | G41: 20 - SUCRE GLACE | H41: DF5 | I41: SEC LOURD | J41: 16 | K41: 28 | L41: 45 | M41: 20160 | N41: 1 | O41: 1 | P41: FALSE
A42: 247821 | B42: 840801001001 | C42: *SUCRE GRAIN N6 BS SAC 5KG | D42: 52 - POLE SUCREE | E42: 382 - SUCRE ET EDULCORANT | F42: 10 - SUCRE BLANC | G42: 40 - RAFFINE > 1KG | H42: DF1 | I42: SEC LOURD | J42: 13 | K42: 20 | L42: 38 | M42: 9880 | N42: 1 | O42: 1 | P42: FALSE
A43: 247068 | B43: 839621001002 | C43: *SUCRE MCX BLC N 4 1KG ROCHAMB | D43: 52 - POLE SUCREE | E43: 382 - SUCRE ET EDULCORANT | F43: 10 - SUCRE BLANC | G43: 20 - RAFFINE PORTIONS CUBES | H43: DF1 | I43: SEC | J43: 17.5 | K43: 16.5 | L43: 23 | M43: 6641.25 | N43: 6 | O43: 6 | P43: FALSE
A44: 247774 | B44: 840757001001 | C44: *SUCRE SEMOULE PAT BS SAC 25KG | D44: 52 - POLE SUCREE | E44: 382 - SUCRE ET EDULCORANT | F44: 10 - SUCRE BLANC | G44: 40 - RAFFINE > 1KG | H44: DF1 | I44: SEC LOURD | J44: 76 | K44: 38 | L44: 11.5 | M44: 33212 | N44: 1 | O44: 1 | P44: FALSE
A45: 247805 | B45: 840786001001 | C45: *SUCRE VERGEOISE BLONDE 5KG | D45: 52 - POLE SUCREE | E45: 382 - SUCRE ET EDULCORANT | F45: 30 - SUCRE BRUN | G45: 25 - BLOND/SUCRE VERGEOISE | H45: DF5 | I45: SEC LOURD | J45: 30 | K45: 11 | L45: 47 | M45: 15510 | N45: 1 | O45: 1 | P45: FALSE
A46: 163202 | B46: 162008001001 | C46: *TAHINA CREME SESAME POT 454G | D46: 52 - POLE SUCREE | E46: 400 - INGREDIENTS BOUL/PAT | F46: 30 - INGREDIENTS PATISSERIE | G46: 45 - PATE DE NOIX SECHE | H46: DF1 | I46: SEC | J46: 6.9 | K46: 6.9 | L46: 12.9 | M46: 614.169 | N46: 1 | O46: 12 | P46: FALSE
A47: 304329 | B47: 892476001001 | C47: 01 CONSIGNE DEMI-PALETTE EUROPE | D47: 09 - SA Inconnu (VIDE) | E47: 055 - EMBALLAGE VIDE | F47: 01 - EMBALLAGE VIDE | G47: 01 - EMBALLAGE VIDE | H47: DF1 | I47: Palette Consigne
A48: 305290 | B48: 893404001001 | C48: 02 CONSIGNE PALETTE EUROPE | D48: 09 - SA Inconnu (VIDE) | E48: 055 - EMBALLAGE VIDE | F48: 01 - EMBALLAGE VIDE | G48: 01 - EMBALLAGE VIDE | H48: DF1 | I48: Palette Consigne
A49: 308345 | B49: 896247001001 | C49: 03 CONSIGNE PALETTE PERDUE | D49: 09 - SA Inconnu (VIDE) | E49: 055 - EMBALLAGE VIDE | F49: 01 - EMBALLAGE VIDE | G49: 01 - EMBALLAGE VIDE | H49: DF1 | I49: Palette Consigne
A50: 241288 | B50: 834759001001 | C50: 04 PALETTE PERDUE | D50: 09 - SA Inconnu (VIDE) | E50: 073 - PRESTATION NON FOOD | F50: 04 - SUPPORTS PREPARATION | G50: 01 - ROLLS | H50: DF1 | I50: Palette Consigne
A51: 309450 | B51: 897072001001 | C51: 05 CONSIGNE DEMI-PALETTE PLASTIQUE | D51: 09 - SA Inconnu (VIDE) | E51: 055 - EMBALLAGE VIDE | F51: 01 - EMBALLAGE VIDE | G51: 01 - EMBALLAGE VIDE | H51: DF1 | I51: Palette Consigne
A52: 50415 | B52: 649783001001 | C52: 1/16 GORGON AOP 750GENV MC | D52: 60 - CREMERIE | E52: 225 - PATE PERSILLEE | F52: 40 - GORGONZOLA | G52: 54 - PLUS QUE 500 G | H52: DF1 | I52: CREMERIE | J52: 9 | K52: 15 | L52: 9 | M52: 1215 | N52: 1 | O52: 1 | P52: TRUE
A53: 235432 | B53: 829360001001 | C53: 1/16CANTAL AOP JNE 2,5KGENVCPV | D53: 60 - CREMERIE | E53: 224 - PATE DEMI-MOLLE/DEMI-DURE | F53: 08 - CANTAL | G53: 52 - 500 - 1000 G | H53: DF5 | I53: CREMERIE | J53: 15 | K53: 19.5 | L53: 14 | M53: 4095 | N53: 1 | O53: 1 | P53: TRUE
A54: 236496 | B54: 829275001001 | C54: 1/16COMTE AOP 4M 2,3KGENV ER | D54: 60 - CREMERIE | E54: 220 - FROMAGE A PATE DURE | F54: 12 - COMTE | G54: 47 - PLUS QUE 350 G | H54: DF1 | I54: CREMERIE | J54: 13.8 | K54: 34 | L54: 10 | M54: 4692 | N54: 1 | O54: 1 | P54: TRUE
A55: 294111 | B55: 883437001001 | C55: 1/16COMTE AOP 6M 2,3KG ENV RJ | D55: 60 - CREMERIE | E55: 220 - FROMAGE A PATE DURE | F55: 12 - COMTE | G55: 47 - PLUS QUE 350 G | H55: DF1 | I55: CREMERIE | J55: 10 | K55: 37 | L55: 11 | M55: 4070 | N55: 1 | O55: 1 | P55: TRUE
A56: 162563 | B56: 161516001001 | C56: 1/2 APPENZEL SUR 5M 3.5KGENV | D56: 60 - CREMERIE | E56: 224 - PATE DEMI-MOLLE/DEMI-DURE | F56: 04 - APPENZELL | G56: 20 - CUBES | H56: DF5 | I56: CREMERIE | N56: 1 | O56: 1 | P56: TRUE
A57: 73745 | B57: 665419001001 | C57: 1/2 BAGUETTE PRECUIT 6X140G MC | D57: 66 - TRAITEUR | E57: 201 - PAIN LONGUE CONSERVATION | F57: 40 - PETIT PAIN SPECIAUX | G57: 10 - PETIT PAIN | H57: DF1 | I57: TRAITEUR | J57: 35 | K57: 24.8 | L57: 12 | M57: 10416 | N57: 1 | O57: 9 | P57: FALSE
A58: 50075 | B58: 628210001001 | C58: 1/2 BLOC VIANDE GRISONS 1KGENV | D58: 63 - CHARCUTERIE | E58: 272 - JAMBON ET VIANDE SEC | F58: 50 - B¿UF SECHE | G58: 10 - VIANDE DE GRISONS | H58: DF1 | I58: CHARCUTERIE | J58: 14 | K58: 11 | L58: 6 | M58: 924 | N58: 1 | O58: 1 | P58: TRUE
A59: 5577 | B59: 673446001001 | C59: 1/2 BRESAOLA PUNTAANCA 1.7KENV | D59: 63 - CHARCUTERIE | E59: 272 - JAMBON ET VIANDE SEC | F59: 45 - BRESAOLA | G59: 30 - BRESAOLA GENERIQUE | H59: DF1 | I59: CHARCUTERIE | J59: 8 | K59: 18 | L59: 8 | M59: 1152 | N59: 1 | O59: 1 | P59: TRUE
A60: 63817 | B60: 687209001001 | C60: 1/2 BRIE MEAUX AOP 1/2 AFF MDF | D60: 60 - CREMERIE | E60: 228 - FROMAGE A PATE MOLLE AFFINEE | F60: 15 - BRIE AOP/IGP | G60: 64 - PLUS QUE 1000 G | H60: DF1 | I60: CREMERIE | J60: 17.8 | K60: 3.5 | L60: 35.5 | M60: 2211.65 | N60: 1 | O60: 1 | P60: TRUE
A61: 238900 | B61: 832588001001 | C61: 1/2 BRIE MEAUX AOP 3/4 AFF MDF | D61: 60 - CREMERIE | E61: 228 - FROMAGE A PATE MOLLE AFFINEE | F61: 15 - BRIE AOP/IGP | G61: 64 - PLUS QUE 1000 G | H61: DF1 | I61: CREMERIE | J61: 3.5 | K61: 17.8 | L61: 35.5 | M61: 2211.65 | N61: 1 | O61: 1 | P61: TRUE
A62: 78661 | B62: 666024001001 | C62: 1/2 BRIQUE PUR BREBIS KG | D62: 60 - CREMERIE | E62: 227 - CHEVRE/BREBIS | F62: 10 - BREBIS | G62: 43 - PLUS QUE 250 g | H62: DF5 | I62: CREMERIE | J62: 10 | K62: 14.5 | L62: 7 | M62: 1015 | N62: 1 | O62: 1 | P62: TRUE
A63: 10430 | B63: 210428001001 | C63: 1/2 CARRE COTE CHARO S/P MC | D63: 62 - BOUCHERIE | E63: 310 - BOEUF FRAIS | F63: 53 - CHAROLAISE | G63: 72 - ALOYAU | H63: DF1 | I63: BOUCHERIE | N63: 1 | O63: 1 | P63: TRUE
A64: 287850 | B64: 877899001001 | C64: 1/2 CARRE VEAU DVTB SV EAF MC | D64: 62 - BOUCHERIE | E64: 318 - VEAU FRAIS | F64: 15 - VEAU BLANC EUROPE | G64: 50 - CARRE | H64: DF1 | I64: BOUCHERIE | J64: 15 | K64: 15 | L64: 5 | M64: 1125 | N64: 1 | O64: 1 | P64: TRUE
A65: 9545 | B65: 209543001001 | C65: 1/2 CARRE VX 8C DET S/V EAF MC | D65: 62 - BOUCHERIE | E65: 318 - VEAU FRAIS | F65: 15 - VEAU BLANC EUROPE | G65: 50 - CARRE | H65: DF1 | I65: BOUCHERIE | J65: 39.4 | K65: 29.2 | L65: 10.8 | M65: 12425.184
A66: 289727 | B66: 879608001001 | C66: 1/2 CARRE VX AVEYR SV IGP LR | D66: 62 - BOUCHERIE | E66: 318 - VEAU FRAIS | F66: 50 - AUTRES VEAUX | G66: 62 - AOP/IGP/RACE REGIONALE | H66: DF1 | I66: BOUCHERIE | J66: 20 | K66: 15 | L66: 10 | M66: 3000 | N66: 1 | O66: 1 | P66: TRUE
A67: 174652 | B67: 171718001001 | C67: 1/2 CHORIZO LEON FORT 500G ENV | D67: 63 - CHARCUTERIE | E67: 277 - SAUCISSE | F67: 20 - SAUCISSE SECHE | G67: 12 - CHORIZO BLANC | H67: DF1 | I67: CHARCUTERIE | J67: 9 | K67: 36.5 | L67: 4.5 | M67: 1478.25 | N67: 1 | O67: 1 | P67: TRUE
A68: 236535 | B68: 829314001001 | C68: 1/2 COPPA 1,5KGENV SEL SEC SV | D68: 63 - CHARCUTERIE | E68: 272 - JAMBON ET VIANDE SEC | F68: 60 - COPPA | G68: 10 - COPPA | H68: DF1 | I68: CHARCUTERIE | J68: 9 | K68: 20 | L68: 9 | M68: 1620 | N68: 1 | O68: 1 | P68: TRUE
A69: 236098 | B69: 829566001001 | C69: 1/2 ECHINE FUM S/OS SV-2KG ENV | D69: 63 - CHARCUTERIE | E69: 272 - JAMBON ET VIANDE SEC | F69: 70 - ECHINE | G69: 10 - ECHINE | H69: DF1 | I69: CHARCUTERIE | J69: 20 | K69: 35 | L69: 10 | M69: 7000 | N69: 1 | O69: 1
A70: 10432 | B70: 210430001001 | C70: 1/2 ENTRECOTE CHARO S/P MC | D70: 62 - BOUCHERIE | E70: 310 - BOEUF FRAIS | F70: 53 - CHAROLAISE | G70: 72 - ALOYAU | H70: DF1 | I70: BOUCHERIE | J70: 28 | K70: 18 | L70: 28 | M70: 14112 | N70: 1 | O70: 1 | P70: TRUE
A71: 197114 | B71: 391369001001 | C71: 1/2 ENTRECOTE LIMOUSIN S/P MC | D71: 62 - BOUCHERIE | E71: 310 - BOEUF FRAIS | F71: 54 - LIMOUSINE | G71: 72 - ALOYAU | H71: DF1 | I71: BOUCHERIE | J71: 25 | K71: 22 | L71: 14 | M71: 7700 | N71: 1 | O71: 1 | P71: TRUE
A72: 254678 | B72: 847697001001 | C72: 1/2 ENTRECOTE MONTB S/P MC | D72: 62 - BOUCHERIE | E72: 310 - BOEUF FRAIS | F72: 56 - MONTBELIARDE | G72: 72 - ALOYAU | H72: DF1 | I72: BOUCHERIE | J72: 17 | K72: 27 | L72: 11 | M72: 5049 | N72: 1 | O72: 1 | P72: TRUE
A73: 40156 | B73: 661196001001 | C73: 1/2 ENTRECOTE NORMANDE S/P MC | D73: 62 - BOUCHERIE | E73: 310 - BOEUF FRAIS | F73: 55 - NORMANDE | G73: 72 - ALOYAU | H73: DF1 | I73: BOUCHERIE | J73: 2.2 | K73: 18 | L73: 9 | M73: 356.4
A74: 299740 | B74: 888736001001 | C74: 1/2 ENTRECOTE VBF S/P MC | D74: 62 - BOUCHERIE | E74: 310 - BOEUF FRAIS | F74: 43 - B¿UF NATIONAL (ABATTAGE LOCAL) | G74: 06 - ENTRECOTE | H74: DF1 | I74: BOUCHERIE | N74: 1 | O74: 1 | P74: TRUE
A75: 80298 | B75: 680812001001 | C75: 1/2 FILET BACON 1,3KG ENV | D75: 63 - CHARCUTERIE | E75: 271 - BACON - LARD - LARDON | F75: 10 - BACON CUIT | G75: 46 - BACON SECHE | H75: DF5 | I75: CHARCUTERIE | J75: 9 | K75: 15 | L75: 9 | M75: 1215 | N75: 1 | O75: 1 | P75: TRUE
A76: 199207 | B76: 393495001001 | C76: 1/2 FROMAGE PESTO ROUGE 2,5KGENV | D76: 60 - CREMERIE | E76: 224 - PATE DEMI-MOLLE/DEMI-DURE | F76: 22 - GOUDA | G76: 68 - 1001 - 3500 G | H76: DF1 | I76: CREMERIE | J76: 24 | K76: 12 | L76: 10 | M76: 2880 | N76: 1 | O76: 1 | P76: TRUE
A77: 199205 | B77: 393493001001 | C77: 1/2 FROMAGE PESTO VERT 2,5KG ENV | D77: 60 - CREMERIE | E77: 224 - PATE DEMI-MOLLE/DEMI-DURE | F77: 22 - GOUDA | G77: 68 - 1001 - 3500 G | H77: DF1 | I77: CREMERIE | J77: 24 | K77: 12 | L77: 10 | M77: 2880 | N77: 1 | O77: 1 | P77: TRUE
A78: 189706 | B78: 384581001001 | C78: 1/2 FX FILET 2,7+ VBF S/P | D78: 62 - BOUCHERIE | E78: 310 - BOEUF FRAIS | F78: 43 - B¿UF NATIONAL (ABATTAGE LOCAL) | G78: 63 - FAUX-FILET | H78: DF1 | I78: BOUCHERIE | J78: 0.1 | K78: 0.1 | L78: 0.1 | M78: 0.001 | N78: 1 | O78: 1 | P78: TRUE
A79: 290200 | B79: 879984001001 | C79: 1/2 FX FILET 2,7+ VBF S/P MC | D79: 62 - BOUCHERIE | E79: 310 - BOEUF FRAIS | F79: 43 - B¿UF NATIONAL (ABATTAGE LOCAL) | G79: 63 - FAUX-FILET | H79: DF1 | I79: BOUCHERIE | J79: 27 | K79: 18 | L79: 10 | M79: 4860 | N79: 1 | O79: 1
A80: 227625 | B80: 821013001001 | C80: 1/2 FX FILET 2.5KG+ SIMM UE | D80: 62 - BOUCHERIE | E80: 310 - BOEUF FRAIS | F80: 64 - SIMMENTAL | G80: 63 - FAUX-FILET | H80: DF5 | I80: BOUCHERIE | J80: 28 | K80: 20 | L80: 7 | M80: 3920 | N80: 1 | O80: 1 | P80: TRUE
A81: 234629 | B81: 828805001001 | C81: 1/2 FX FILET 3.7+ S/P UE | D81: 62 - BOUCHERIE | E81: 310 - BOEUF FRAIS | F81: 41 - EUROPE | G81: 63 - FAUX-FILET | H81: DF5 | I81: BOUCHERIE | J81: 30 | K81: 16 | L81: 6 | M81: 2880 | N81: 1 | O81: 1 | P81: TRUE
A82: 85598 | B82: 651981001001 | C82: 1/2 FX FILET ANGUS IRL | D82: 62 - BOUCHERIE | E82: 310 - BOEUF FRAIS | F82: 70 - HEREFORD | G82: 63 - FAUX-FILET | H82: DF1 | I82: BOUCHERIE | N82: 1 | O82: 1 | P82: TRUE
A83: 10405 | B83: 210403001001 | C83: 1/2 FX FILET CHARO S/P MC | D83: 62 - BOUCHERIE | E83: 310 - BOEUF FRAIS | F83: 53 - CHAROLAISE | G83: 63 - FAUX-FILET | H83: DF1 | I83: BOUCHERIE | J83: 0 | K83: 0 | L83: 0 | M83: 0 | N83: 1 | O83: 1 | P83: TRUE
A84: 19246 | B84: 674699001001 | C84: 1/2 FX FILET LIMOUSIN S/P MC | D84: 62 - BOUCHERIE | E84: 310 - BOEUF FRAIS | F84: 54 - LIMOUSINE | G84: 63 - FAUX-FILET | H84: DF1 | I84: BOUCHERIE | J84: 31 | K84: 24 | L84: 10 | M84: 7440 | N84: 1 | O84: 1 | P84: TRUE
A85: 182626 | B85: 179336001001 | C85: 1/2 FX FILET MONTB S/P MC | D85: 62 - BOUCHERIE | E85: 310 - BOEUF FRAIS | F85: 56 - MONTBELIARDE | G85: 63 - FAUX-FILET | H85: DF1 | I85: BOUCHERIE | J85: 0 | K85: 0 | L85: 0 | M85: 0 | N85: 1 | O85: 1
A86: 46110 | B86: 243108001001 | C86: 1/2 FX FILET NORMAND S/P MC | D86: 62 - BOUCHERIE | E86: 310 - BOEUF FRAIS | F86: 55 - NORMANDE | G86: 63 - FAUX-FILET | H86: DF1 | I86: BOUCHERIE | J86: 30 | K86: 20 | L86: 15 | M86: 9000 | N86: 1 | O86: 1 | P86: TRUE
A87: 305917 | B87: 893978001001 | C87: 1/2 FX FILET S/P 3KG+ IRL MC | D87: 62 - BOUCHERIE | E87: 310 - BOEUF FRAIS | F87: 41 - EUROPE | G87: 63 - FAUX-FILET | H87: DF1 | I87: BOUCHERIE | N87: 1 | O87: 1 | P87: TRUE
A88: 12402 | B88: 212400001001 | C88: 1/2 FX FILET SALERS S/P | D88: 62 - BOUCHERIE | E88: 310 - BOEUF FRAIS | F88: 57 - SALERS | G88: 63 - FAUX-FILET | H88: DF5 | I88: BOUCHERIE | J88: 8.5 | K88: 4 | L88: 13.5 | M88: 459 | N88: 1 | O88: 1
A89: 157137 | B89: 156042001001 | C89: 1/2 GORGON AOP CUILLERE 6KGENV | D89: 60 - CREMERIE | E89: 225 - PATE PERSILLEE | F89: 40 - GORGONZOLA | G89: 54 - PLUS QUE 500 G | H89: DF5 | I89: CREMERIE | J89: 30 | K89: 30 | L89: 17 | M89: 15300 | N89: 1 | O89: 1 | P89: TRUE
A90: 199218 | B90: 393507001001 | C90: 1/2 GOUDA AUX TRUFFES 4KG ENV | D90: 60 - CREMERIE | E90: 224 - PATE DEMI-MOLLE/DEMI-DURE | F90: 22 - GOUDA | G90: 68 - 1001 - 3500 G | H90: DF5 | I90: CREMERIE | J90: 29 | K90: 14.5 | L90: 13 | M90: 5466.5 | N90: 1 | O90: 1 | P90: TRUE
A91: 296616 | B91: 885861001001 | C91: 1/2 JB FUME 3KG ENV MC VPF | D91: 63 - CHARCUTERIE | E91: 273 - JAMBON CUIT | F91: 10 - JAMBON CUIT DE PORC | G91: 72 - JB CUIT FUME | H91: DF1 | I91: CHARCUTERIE | N91: 1 | O91: 1 | P91: TRUE
A92: 236493 | B92: 829272001001 | C92: 1/2 JB FUME DOUGRILL 3,5KG ENV | D92: 63 - CHARCUTERIE | E92: 273 - JAMBON CUIT | F92: 27310 - JAMBON CUIT DE PORC | G92: 2731072 - JB CUIT FUME | I92: CHARCUTERIE | N92: 1 | O92: 1 | P92: TRUE
A93: 235459 | B93: 829387001001 | C93: 1/2 JB PARME RASP 3,4K ENV 14M | D93: 63 - CHARCUTERIE | E93: 272 - JAMBON ET VIANDE SEC | F93: 10 - JAMBON SEC ITALIEN | G93: 20 - PIECE DE JB DE PARME | H93: DF1 | I93: CHARCUTERIE | J93: 40 | K93: 15 | L93: 8 | M93: 4800 | N93: 1 | O93: 1 | P93: TRUE
A94: 236537 | B94: 829316001001 | C94: 1/2 JB SAN DANIELE 3.7KENV 13M | D94: 63 - CHARCUTERIE | E94: 272 - JAMBON ET VIANDE SEC | F94: 10 - JAMBON SEC ITALIEN | G94: 40 - PIECE DE JB SAN DANIELE | H94: DF5 | I94: CHARCUTERIE | J94: 38 | K94: 15 | L94: 8 | M94: 4560 | N94: 1 | O94: 1 | P94: TRUE
A95: 252399 | B95: 844769001001 | C95: 1/2 JB SERAN.BASQU S/O 10 MOIS | D95: 63 - CHARCUTERIE | E95: 272 - JAMBON ET VIANDE SEC | F95: 05 - JAMBON SEC ESPAGNOL | G95: 28 - JB BLANCO S/O - 10 MOIS | H95: DF5 | I95: CHARCUTERIE | N95: 1 | O95: 1 | P95: TRUE
A96: 158104 | B96: 157070001001 | C96: 1/2 JB SPECK 2,5KG ENV 3M | D96: 63 - CHARCUTERIE | E96: 272 - JAMBON ET VIANDE SEC | F96: 30 - JAMBON SPECK | G96: 65 - AUTRES JB SPECK | H96: DF1 | I96: CHARCUTERIE | J96: 18 | K96: 27 | L96: 7 | M96: 3402 | N96: 1 | O96: 1 | P96: TRUE
A97: 236514 | B97: 829293001001 | C97: 1/2 JB SUP 4KG ENV AC LE FOUE | D97: 63 - CHARCUTERIE | E97: 273 - JAMBON CUIT | F97: 10 - JAMBON CUIT DE PORC | G97: 40 - JB CUIT SUP AC | H97: DF1 | I97: CHARCUTERIE | J97: 12 | K97: 22 | L97: 18.5 | M97: 4884 | N97: 1 | O97: 1 | P97: TRUE
A98: 235421 | B98: 829349001001 | C98: 1/2 JB SUP AC 3,6KG ENV ARGOAT | D98: 63 - CHARCUTERIE | E98: 273 - JAMBON CUIT | F98: 10 - JAMBON CUIT DE PORC | G98: 40 - JB CUIT SUP AC | H98: DF5 | I98: CHARCUTERIE | J98: 11.5 | K98: 20.5 | L98: 17 | M98: 4007.75 | N98: 1 | O98: 1 | P98: TRUE
A99: 235422 | B99: 829350001001 | C99: 1/2 JB SUP DD 3,6KG ENV ARGOAT | D99: 63 - CHARCUTERIE | E99: 273 - JAMBON CUIT | F99: 10 - JAMBON CUIT DE PORC | G99: 45 - JB CUIT SUP DD | H99: DF1 | I99: CHARCUTERIE | J99: 11.5 | K99: 20.5 | L99: 17 | M99: 4007.75 | N99: 1 | O99: 1 | P99: TRUE
A100: 43827 | B100: 671754001001 | C100: 1/2 JB SUP DD 4KG ENV LE FOUE | D100: 63 - CHARCUTERIE | E100: 273 - JAMBON CUIT | F100: 10 - JAMBON CUIT DE PORC | G100: 45 - JB CUIT SUP DD | H100: DF5+ | I100: CHARCUTERIE | J100: 15 | K100: 22 | L100: 11 | M100: 3630 | N100: 1 | O100: 1 | P100: TRUE
...

Sheet Ref Unité VS Pack
A1: Ref METRO | B1: MGB | C1: Gauche | D1: Packaging | E1: Libellé Article | F1: Conditionnement Vente | G1: Conditionnement fournisseur | H1: Vendu au poids | I1: en stock ?
A2: 236386 | B2: 829930001001 | C2: =LEFT(B2,11) -> 82993000100 | D2: =RIGHT(B2,1) -> 1 | E2: AEROSOL SUCREE 250ML WHIPPY | F2: 1 | G2: 12 | H2: FALSE | I2: =COUNTIF(#REF!,'Ref Unité VS Pack'!B2) -> #REF!
A3: 236387 | B3: 829930001002 | C3: =LEFT(B3,11) -> 82993000100 | D3: =RIGHT(B3,1) -> 2 | E3: AEROSOL SUCREE 250ML WHIPPY | F3: 12 | G3: 12 | H3: FALSE | I3: =COUNTIF(#REF!,'Ref Unité VS Pack'!B3) -> #REF!
A4: 72233 | B4: 657496001001 | C4: =LEFT(B4,11) -> 65749600100 | D4: =RIGHT(B4,1) -> 1 | E4: AIGUILLETTE PLTHAL IQF 1KG UE | F4: 1 | G4: 4 | H4: FALSE | I4: =COUNTIF(#REF!,'Ref Unité VS Pack'!B4) -> #REF!
A5: 166664 | B5: 657496001002 | C5: =LEFT(B5,11) -> 65749600100 | D5: =RIGHT(B5,1) -> 2 | E5: AIGUILLETTE PLTHAL IQF 1KG UE | H5: FALSE | I5: =COUNTIF(#REF!,'Ref Unité VS Pack'!B5) -> #REF!
A6: 187191 | B6: 382099001001 | C6: =LEFT(B6,11) -> 38209900100 | D6: =RIGHT(B6,1) -> 1 | E6: ALLUMETTE FUM BOIS HETR 1KG MC | F6: 1 | G6: 6 | H6: FALSE | I6: =COUNTIF(#REF!,'Ref Unité VS Pack'!B6) -> #REF!
A7: 239431 | B7: 382099001002 | C7: =LEFT(B7,11) -> 38209900100 | D7: =RIGHT(B7,1) -> 2 | E7: ALLUMETTE FUM BOIS HETR 1KG MC | H7: FALSE | I7: =COUNTIF(#REF!,'Ref Unité VS Pack'!B7) -> #REF!
A8: 187181 | B8: 382090001001 | C8: =LEFT(B8,11) -> 38209000100 | D8: =RIGHT(B8,1) -> 1 | E8: ALLUMETTE NATURE 1KG MC | F8: 1 | G8: 6 | H8: FALSE | I8: =COUNTIF(#REF!,'Ref Unité VS Pack'!B8) -> #REF!
A9: 239436 | B9: 382090001002 | C9: =LEFT(B9,11) -> 38209000100 | D9: =RIGHT(B9,1) -> 2 | E9: ALLUMETTE NATURE 1KG MC | H9: FALSE | I9: =COUNTIF(#REF!,'Ref Unité VS Pack'!B9) -> #REF!
A10: 192596 | B10: 387559001001 | C10: =LEFT(B10,11) -> 38755900100 | D10: =RIGHT(B10,1) -> 1 | E10: AMERICANO DOB 16D 1L | F10: 1 | G10: 6 | H10: FALSE | I10: =COUNTIF(#REF!,'Ref Unité VS Pack'!B10) -> #REF!
A11: 210887 | B11: 387559001002 | C11: =LEFT(B11,11) -> 38755900100 | D11: =RIGHT(B11,1) -> 2 | E11: AMERICANO DOB 16D 1L | H11: FALSE | I11: =COUNTIF(#REF!,'Ref Unité VS Pack'!B11) -> #REF!
A12: 296129 | B12: 885385001001 | C12: =LEFT(B12,11) -> 88538500100 | D12: =RIGHT(B12,1) -> 1 | E12: APERITIVO DELAITRE 12,5D 1L | F12: 1 | G12: 6 | H12: FALSE | I12: =COUNTIF(#REF!,'Ref Unité VS Pack'!B12) -> #REF!
A13: 296479 | B13: 885385001002 | C13: =LEFT(B13,11) -> 88538500100 | D13: =RIGHT(B13,1) -> 2 | E13: APERITIVO DELAITRE 12,5D 1L | H13: FALSE | I13: =COUNTIF(#REF!,'Ref Unité VS Pack'!B13) -> #REF!
A14: 285097 | B14: 875505001001 | C14: =LEFT(B14,11) -> 87550500100 | D14: =RIGHT(B14,1) -> 1 | E14: APEROL 12,5D 1L | F14: 1 | G14: 6 | H14: FALSE | I14: =COUNTIF(#REF!,'Ref Unité VS Pack'!B14) -> #REF!
A15: 285189 | B15: 875505001002 | C15: =LEFT(B15,11) -> 87550500100 | D15: =RIGHT(B15,1) -> 2 | E15: APEROL 12,5D 1L | H15: FALSE | I15: =COUNTIF(#REF!,'Ref Unité VS Pack'!B15) -> #REF!
A16: 306258 | B16: 894297001001 | C16: =LEFT(B16,11) -> 89429700100 | D16: =RIGHT(B16,1) -> 1 | E16: ARO HLE COLZA 1L | F16: 1 | G16: 15 | H16: FALSE | I16: =COUNTIF(#REF!,'Ref Unité VS Pack'!B16) -> #REF!
A17: 184044 | B17: 894297001002 | C17: =LEFT(B17,11) -> 89429700100 | D17: =RIGHT(B17,1) -> 2 | E17: ARO HLE COLZA 1L | H17: FALSE | I17: =COUNTIF(#REF!,'Ref Unité VS Pack'!B17) -> #REF!
A18: 187405 | C18: =LEFT(B18,11) | D18: =RIGHT(B18,1) | E18: ARO PULPE DE TOMATE AU JUS 5/1 | H18: FALSE | I18: =COUNTIF(#REF!,'Ref Unité VS Pack'!B18) -> #REF!
A19: 762011 | C19: =LEFT(B19,11) | D19: =RIGHT(B19,1) | E19: AVO HASS FILET C.227/274G PC4 C1 IL ISRAEL | H19: FALSE | I19: =COUNTIF(#REF!,'Ref Unité VS Pack'!B19) -> #REF!
A20: 192676 | B20: 387642001001 | C20: =LEFT(B20,11) -> 38764200100 | D20: =RIGHT(B20,1) -> 1 | E20: BAILEYS IRISH CREME 17D 70CL | F20: 1 | G20: 6 | H20: FALSE | I20: =COUNTIF(#REF!,'Ref Unité VS Pack'!B20) -> #REF!
A21: 248051 | B21: 387642001002 | C21: =LEFT(B21,11) -> 38764200100 | D21: =RIGHT(B21,1) -> 2 | E21: BAILEYS IRISH CREME 17D 70CL | H21: FALSE | I21: =COUNTIF(#REF!,'Ref Unité VS Pack'!B21) -> #REF!
A22: 231272 | B22: 824733001001 | C22: =LEFT(B22,11) -> 82473300100 | D22: =RIGHT(B22,1) -> 1 | E22: BANDOL RSE GALETS 75CL MIL | F22: 1 | G22: 6 | H22: FALSE | I22: =COUNTIF(#REF!,'Ref Unité VS Pack'!B22) -> #REF!
A23: 231273 | B23: 824733001002 | C23: =LEFT(B23,11) -> 82473300100 | D23: =RIGHT(B23,1) -> 2 | E23: BANDOL RSE GALETS 75CL MIL | H23: FALSE | I23: =COUNTIF(#REF!,'Ref Unité VS Pack'!B23) -> #REF!
A24: 302035 | B24: 890989001001 | C24: =LEFT(B24,11) -> 89098900100 | D24: =RIGHT(B24,1) -> 1 | E24: BEAUSEJOUR HOST HT MED 75CL | F24: 1 | G24: 6 | H24: FALSE | I24: =COUNTIF(#REF!,'Ref Unité VS Pack'!B24) -> #REF!
A25: 302036 | B25: 890989001002 | C25: =LEFT(B25,11) -> 89098900100 | D25: =RIGHT(B25,1) -> 2 | E25: BEAUSEJOUR HOST HT MED 75CL | H25: FALSE | I25: =COUNTIF(#REF!,'Ref Unité VS Pack'!B25) -> #REF!
A26: 225209 | B26: 818750001001 | C26: =LEFT(B26,11) -> 81875000100 | D26: =RIGHT(B26,1) -> 1 | E26: BEURRE DS 500G MA PAYSANNE | F26: 1 | G26: 20 | H26: FALSE | I26: =COUNTIF(#REF!,'Ref Unité VS Pack'!B26) -> #REF!
A27: 264597 | B27: 818750001002 | C27: =LEFT(B27,11) -> 81875000100 | D27: =RIGHT(B27,1) -> 2 | E27: BEURRE DS 500G MA PAYSANNE | H27: FALSE | I27: =COUNTIF(#REF!,'Ref Unité VS Pack'!B27) -> #REF!
A28: 225210 | B28: 818751001001 | C28: =LEFT(B28,11) -> 81875100100 | D28: =RIGHT(B28,1) -> 1 | E28: BEURRE DX 500G MA PAYSANNE | F28: 1 | G28: 20 | H28: FALSE | I28: =COUNTIF(#REF!,'Ref Unité VS Pack'!B28) -> #REF!
A29: 264605 | B29: 818751001002 | C29: =LEFT(B29,11) -> 81875100100 | D29: =RIGHT(B29,1) -> 2 | E29: BEURRE DX 500G MA PAYSANNE | H29: FALSE | I29: =COUNTIF(#REF!,'Ref Unité VS Pack'!B29) -> #REF!
A30: 247852 | B30: 840832001001 | C30: =LEFT(B30,11) -> 84083200100 | D30: =RIGHT(B30,1) -> 1 | E30: BEURRE DX 500G PRESID.PROF | F30: 1 | G30: 20 | H30: FALSE | I30: =COUNTIF(#REF!,'Ref Unité VS Pack'!B30) -> #REF!
A31: 247853 | B31: 840832001002 | C31: =LEFT(B31,11) -> 84083200100 | D31: =RIGHT(B31,1) -> 2 | E31: BEURRE DX 500G PRESID.PROF | H31: FALSE | I31: =COUNTIF(#REF!,'Ref Unité VS Pack'!B31) -> #REF!
A32: 297475 | B32: 886562001001 | C32: =LEFT(B32,11) -> 88656200100 | D32: =RIGHT(B32,1) -> 1 | E32: BEURRE DX PLQ 500G METRO CHEF | F32: 1 | G32: 20 | H32: FALSE | I32: =COUNTIF(#REF!,'Ref Unité VS Pack'!B32) -> #REF!
A33: 298197 | B33: 886562001002 | C33: =LEFT(B33,11) -> 88656200100 | D33: =RIGHT(B33,1) -> 2 | E33: BEURRE DX PLQ 500G METRO CHEF | F33: 20 | G33: 20 | H33: FALSE | I33: =COUNTIF(#REF!,'Ref Unité VS Pack'!B33) -> #REF!
A34: 269860 | B34: 861758001001 | C34: =LEFT(B34,11) -> 86175800100 | D34: =RIGHT(B34,1) -> 1 | E34: BEURRE SEC TOUR COLORE 1KG FLD | F34: 1 | G34: 10 | H34: FALSE | I34: =COUNTIF(#REF!,'Ref Unité VS Pack'!B34) -> #REF!
A35: 269861 | B35: 861758001002 | C35: =LEFT(B35,11) -> 86175800100 | D35: =RIGHT(B35,1) -> 2 | E35: BEURRE SEC TOUR COLORE 1KG FLD | H35: FALSE | I35: =COUNTIF(#REF!,'Ref Unité VS Pack'!B35) -> #REF!
A36: 264559 | B36: 857405001001 | C36: =LEFT(B36,11) -> 85740500100 | D36: =RIGHT(B36,1) -> 1 | E36: BEURRE SEC TOURAGE 1KG FLECHAR | F36: 1 | G36: 10 | H36: FALSE | I36: =COUNTIF(#REF!,'Ref Unité VS Pack'!B36) -> #REF!
A37: 264560 | B37: 857405001002 | C37: =LEFT(B37,11) -> 85740500100 | D37: =RIGHT(B37,1) -> 2 | E37: BEURRE SEC TOURAGE 1KG FLECHAR | H37: FALSE | I37: =COUNTIF(#REF!,'Ref Unité VS Pack'!B37) -> #REF!
A38: 188501 | C38: =LEFT(B38,11) | D38: =RIGHT(B38,1) | E38: BOULE MACREUSE HAL UE | H38: TRUE | I38: =COUNTIF(#REF!,'Ref Unité VS Pack'!B38) -> #REF!
A39: 72251 | B39: 636897001001 | C39: =LEFT(B39,11) -> 63689700100 | D39: =RIGHT(B39,1) -> 1 | E39: BOULETTE A L'AGNEAU HALAL 1KG | F39: 1 | G39: 9 | I39: =COUNTIF(#REF!,'Ref Unité VS Pack'!B39) -> #REF!
A40: 166663 | B40: 636897001002 | C40: =LEFT(B40,11) -> 63689700100 | D40: =RIGHT(B40,1) -> 2 | E40: BOULETTE A L'AGNEAU HALAL 1KG | I40: =COUNTIF(#REF!,'Ref Unité VS Pack'!B40) -> #REF!
A41: 57395 | B41: 633970001001 | C41: =LEFT(B41,11) -> 63397000100 | D41: =RIGHT(B41,1) -> 1 | E41: BRANDY CHEVALIER FR 36D 70CL | F41: 1 | G41: 6 | H41: FALSE | I41: =COUNTIF(#REF!,'Ref Unité VS Pack'!B41) -> #REF!
A42: 299427 | B42: 633970001002 | C42: =LEFT(B42,11) -> 63397000100 | D42: =RIGHT(B42,1) -> 2 | E42: BRANDY CHEVALIER FR 36D 70CL | H42: FALSE | I42: =COUNTIF(#REF!,'Ref Unité VS Pack'!B42) -> #REF!
A43: 290935 | B43: 830841001001 | C43: =LEFT(B43,11) -> 83084100100 | D43: =RIGHT(B43,1) -> 1 | E43: BREIZH COLA ZERO 33CL VP | F43: 1 | G43: 18 | H43: FALSE | I43: =COUNTIF(#REF!,'Ref Unité VS Pack'!B43) -> #REF!
A44: 237157 | B44: 830841001002 | C44: =LEFT(B44,11) -> 83084100100 | D44: =RIGHT(B44,1) -> 2 | E44: BREIZH COLA ZERO 33CL VP | F44: 18 | G44: 18 | H44: FALSE | I44: =COUNTIF(#REF!,'Ref Unité VS Pack'!B44) -> #REF!
A45: 216723 | B45: 810519001001 | C45: =LEFT(B45,11) -> 81051900100 | D45: =RIGHT(B45,1) -> 1 | E45: BRG.HCB RGE NUITON B 75CL | F45: 1 | G45: 6 | H45: FALSE | I45: =COUNTIF(#REF!,'Ref Unité VS Pack'!B45) -> #REF!
A46: 216724 | B46: 810519001002 | C46: =LEFT(B46,11) -> 81051900100 | D46: =RIGHT(B46,1) -> 2 | E46: BRG.HCB RGE NUITON B 75CL | H46: FALSE | I46: =COUNTIF(#REF!,'Ref Unité VS Pack'!B46) -> #REF!
A47: 254441 | B47: 847508001001 | C47: =LEFT(B47,11) -> 84750800100 | D47: =RIGHT(B47,1) -> 1 | E47: BS CAPTAIN MORGAN 35D 150CL | F47: 1 | G47: 6 | H47: FALSE | I47: =COUNTIF(#REF!,'Ref Unité VS Pack'!B47) -> #REF!
A48: 254442 | B48: 847508001002 | C48: =LEFT(B48,11) -> 84750800100 | D48: =RIGHT(B48,1) -> 2 | E48: BS CAPTAIN MORGAN 35D 150CL | H48: FALSE | I48: =COUNTIF(#REF!,'Ref Unité VS Pack'!B48) -> #REF!
A49: 254452 | B49: 847513001001 | C49: =LEFT(B49,11) -> 84751300100 | D49: =RIGHT(B49,1) -> 1 | E49: BS CAPTAIN MORGAN 35D 70CL | F49: 1 | G49: 6 | H49: FALSE | I49: =COUNTIF(#REF!,'Ref Unité VS Pack'!B49) -> #REF!
A50: 254453 | B50: 847513001002 | C50: =LEFT(B50,11) -> 84751300100 | D50: =RIGHT(B50,1) -> 2 | E50: BS CAPTAIN MORGAN 35D 70CL | H50: FALSE | I50: =COUNTIF(#REF!,'Ref Unité VS Pack'!B50) -> #REF!
A51: 285107 | B51: 875516001001 | C51: =LEFT(B51,11) -> 87551600100 | D51: =RIGHT(B51,1) -> 1 | E51: BS SPICED DELAITRE 35D 70CL | F51: 1 | G51: 6 | H51: FALSE | I51: =COUNTIF(#REF!,'Ref Unité VS Pack'!B51) -> #REF!
A52: 292623 | B52: 875516001002 | C52: =LEFT(B52,11) -> 87551600100 | D52: =RIGHT(B52,1) -> 2 | E52: BS SPICED DELAITRE 35D 70CL | H52: FALSE | I52: =COUNTIF(#REF!,'Ref Unité VS Pack'!B52) -> #REF!
A53: 269325 | B53: 857155001001 | C53: =LEFT(B53,11) -> 85715500100 | D53: =RIGHT(B53,1) -> 1 | E53: BS TI ANANAS VICTORIA 32D 70CL | F53: 1 | G53: 6 | H53: FALSE | I53: =COUNTIF(#REF!,'Ref Unité VS Pack'!B53) -> #REF!
A54: 285352 | B54: 857155001002 | C54: =LEFT(B54,11) -> 85715500100 | D54: =RIGHT(B54,1) -> 2 | E54: BS TI ANANAS VICTORIA 32D 70CL | H54: FALSE | I54: =COUNTIF(#REF!,'Ref Unité VS Pack'!B54) -> #REF!
A55: 216765 | B55: 810521001001 | C55: =LEFT(B55,11) -> 81052100100 | D55: =RIGHT(B55,1) -> 1 | E55: C. HERM RGE BIO* R.BLOND 75CL | F55: 1 | G55: 6 | H55: FALSE | I55: =COUNTIF(#REF!,'Ref Unité VS Pack'!B55) -> #REF!
A56: 216766 | B56: 810521001002 | C56: =LEFT(B56,11) -> 81052100100 | D56: =RIGHT(B56,1) -> 2 | E56: C. HERM RGE BIO* R.BLOND 75CL | H56: FALSE | I56: =COUNTIF(#REF!,'Ref Unité VS Pack'!B56) -> #REF!
A57: 269174 | B57: 856957001001 | C57: =LEFT(B57,11) -> 85695700100 | D57: =RIGHT(B57,1) -> 1 | E57: CACHACA AGUACANA 37.5D 70CL | F57: 1 | G57: 6 | H57: FALSE | I57: =COUNTIF(#REF!,'Ref Unité VS Pack'!B57) -> #REF!
A58: 269175 | B58: 856957001002 | C58: =LEFT(B58,11) -> 85695700100 | D58: =RIGHT(B58,1) -> 2 | E58: CACHACA AGUACANA 37.5D 70CL | H58: FALSE | I58: =COUNTIF(#REF!,'Ref Unité VS Pack'!B58) -> #REF!
A59: 192550 | B59: 387513001001 | C59: =LEFT(B59,11) -> 38751300100 | D59: =RIGHT(B59,1) -> 1 | E59: CALVADOS DELAITRE 40D 1L | F59: 1 | G59: 6 | H59: FALSE | I59: =COUNTIF(#REF!,'Ref Unité VS Pack'!B59) -> #REF!
A60: 299434 | B60: 387513001002 | C60: =LEFT(B60,11) -> 38751300100 | D60: =RIGHT(B60,1) -> 2 | E60: CALVADOS DELAITRE 40D 1L | H60: FALSE | I60: =COUNTIF(#REF!,'Ref Unité VS Pack'!B60) -> #REF!
A61: 28980 | B61: 225978001001 | C61: =LEFT(B61,11) -> 22597800100 | D61: =RIGHT(B61,1) -> 1 | E61: CAMPARI 25D 1L | F61: 1 | G61: 6 | H61: FALSE | I61: =COUNTIF(#REF!,'Ref Unité VS Pack'!B61) -> #REF!
A62: 300961 | B62: 225978001002 | C62: =LEFT(B62,11) -> 22597800100 | D62: =RIGHT(B62,1) -> 2 | E62: CAMPARI 25D 1L | H62: FALSE | I62: =COUNTIF(#REF!,'Ref Unité VS Pack'!B62) -> #REF!
A63: 39409 | C63: =LEFT(B63,11) | D63: =RIGHT(B63,1) | E63: CARRE 13 COTE AGN S/V NZ | H63: TRUE | I63: =COUNTIF(#REF!,'Ref Unité VS Pack'!B63) -> #REF!
A64: 232150 | B64: 808419001001 | C64: =LEFT(B64,11) -> 80841900100 | D64: =RIGHT(B64,1) -> 1 | E64: CDP CAVALIER MIL RSE 75CL | F64: 1 | G64: 6 | H64: FALSE | I64: =COUNTIF(#REF!,'Ref Unité VS Pack'!B64) -> #REF!
A65: 214119 | B65: 808419001002 | C65: =LEFT(B65,11) -> 80841900100 | D65: =RIGHT(B65,1) -> 2 | E65: CDP CAVALIER MIL RSE 75CL | H65: FALSE | I65: =COUNTIF(#REF!,'Ref Unité VS Pack'!B65) -> #REF!
A66: 221718 | C66: =LEFT(B66,11) | D66: =RIGHT(B66,1) | E66: CDP CH MAUVANN RSE MIL 75CL AO | H66: FALSE | I66: =COUNTIF(#REF!,'Ref Unité VS Pack'!B66) -> #REF!
A67: 221774 | B67: 815671001002 | C67: =LEFT(B67,11) -> 81567100100 | D67: =RIGHT(B67,1) -> 2 | E67: CDP RSE 75CL T. DE BERNE MIL | F67: 6 | G67: 6 | I67: =COUNTIF(#REF!,'Ref Unité VS Pack'!B67) -> #REF!
A68: 221712 | B68: 815588001001 | C68: =LEFT(B68,11) -> 81558800100 | D68: =RIGHT(B68,1) -> 1 | E68: CDP RSE MIL MAGALI AOC 75CL | F68: 1 | G68: 6 | I68: =COUNTIF(#REF!,'Ref Unité VS Pack'!B68) -> #REF!
A69: 221711 | B69: 815588001002 | C69: =LEFT(B69,11) -> 81558800100 | D69: =RIGHT(B69,1) -> 2 | E69: CDP RSE MIL MAGALI AOC 75CL | I69: =COUNTIF(#REF!,'Ref Unité VS Pack'!B69) -> #REF!
A70: 177146 | B70: 174128001001 | C70: =LEFT(B70,11) -> 17412800100 | D70: =RIGHT(B70,1) -> 1 | E70: CDP RSE MIRAVAL 75CL MIL | F70: 1 | G70: 6 | H70: FALSE | I70: =COUNTIF(#REF!,'Ref Unité VS Pack'!B70) -> #REF!
A71: 228490 | B71: 174128001002 | C71: =LEFT(B71,11) -> 17412800100 | D71: =RIGHT(B71,1) -> 2 | E71: CDP RSE MIRAVAL 75CL MIL | H71: FALSE | I71: =COUNTIF(#REF!,'Ref Unité VS Pack'!B71) -> #REF!
A72: 244215 | B72: 807052001001 | C72: =LEFT(B72,11) -> 80705200100 | D72: =RIGHT(B72,1) -> 1 | E72: CH ARCINS HT MEDOC CB 75CL | F72: 1 | G72: 6 | H72: FALSE | I72: =COUNTIF(#REF!,'Ref Unité VS Pack'!B72) -> #REF!
A73: 215253 | B73: 809203001001 | C73: =LEFT(B73,11) -> 80920300100 | D73: =RIGHT(B73,1) -> 1 | E73: CH AYALA BRUT MAJEUR 75CL | F73: 1 | G73: 6 | I73: =COUNTIF(#REF!,'Ref Unité VS Pack'!B73) -> #REF!
A74: 215254 | B74: 809203001002 | C74: =LEFT(B74,11) -> 80920300100 | D74: =RIGHT(B74,1) -> 2 | E74: CH AYALA BRUT MAJEUR 75CL | I74: =COUNTIF(#REF!,'Ref Unité VS Pack'!B74) -> #REF!
A75: 214110 | C75: =LEFT(B75,11) | D75: =RIGHT(B75,1) | E75: CH BESSERAT G. TRAD 75CL | H75: FALSE | I75: =COUNTIF(#REF!,'Ref Unité VS Pack'!B75) -> #REF!
A76: 214109 | B76: 808336001001 | C76: =LEFT(B76,11) -> 80833600100 | D76: =RIGHT(B76,1) -> 1 | E76: CH BESSERAT G. TRAD 75CL | F76: 1 | G76: 6 | I76: =COUNTIF(#REF!,'Ref Unité VS Pack'!B76) -> #REF!
A77: 214110 | B77: 808336001002 | C77: =LEFT(B77,11) -> 80833600100 | D77: =RIGHT(B77,1) -> 2 | E77: CH BESSERAT G. TRAD 75CL | F77: 6 | G77: 6 | I77: =COUNTIF(#REF!,'Ref Unité VS Pack'!B77) -> #REF!
A78: 214442 | B78: 809088001001 | C78: =LEFT(B78,11) -> 80908800100 | D78: =RIGHT(B78,1) -> 1 | E78: CH BOLLINGER 75CL S.CUVEE | F78: 1 | G78: 6 | H78: FALSE | I78: =COUNTIF(#REF!,'Ref Unité VS Pack'!B78) -> #REF!
A79: 214443 | B79: 809088001002 | C79: =LEFT(B79,11) -> 80908800100 | D79: =RIGHT(B79,1) -> 2 | E79: CH BOLLINGER 75CL S.CUVEE | H79: FALSE | I79: =COUNTIF(#REF!,'Ref Unité VS Pack'!B79) -> #REF!
A80: 217597 | B80: 807486001001 | C80: =LEFT(B80,11) -> 80748600100 | D80: =RIGHT(B80,1) -> 1 | E80: CH CHARLES BARR BRT 75CL | F80: 1 | G80: 6 | H80: FALSE | I80: =COUNTIF(#REF!,'Ref Unité VS Pack'!B80) -> #REF!
A81: 213958 | B81: 807486001002 | C81: =LEFT(B81,11) -> 80748600100 | D81: =RIGHT(B81,1) -> 2 | E81: CH CHARLES BARR BRT 75CL | H81: FALSE | I81: =COUNTIF(#REF!,'Ref Unité VS Pack'!B81) -> #REF!
A82: 302751 | B82: 884012001001 | C82: =LEFT(B82,11) -> 88401200100 | D82: =RIGHT(B82,1) -> 1 | E82: CH CLAUZOTS BLC GRAV 75CL | F82: 1 | G82: 6 | H82: FALSE | I82: =COUNTIF(#REF!,'Ref Unité VS Pack'!B82) -> #REF!
A83: 294463 | B83: 884012001002 | C83: =LEFT(B83,11) -> 88401200100 | D83: =RIGHT(B83,1) -> 2 | E83: CH CLAUZOTS BLC GRAV 75CL | H83: FALSE | I83: =COUNTIF(#REF!,'Ref Unité VS Pack'!B83) -> #REF!
A84: 216021 | B84: 808108001001 | C84: =LEFT(B84,11) -> 80810800100 | D84: =RIGHT(B84,1) -> 1 | E84: CH DEUTZ BRUT CLASSIC 75CL | F84: 1 | G84: 6 | I84: =COUNTIF(#REF!,'Ref Unité VS Pack'!B84) -> #REF!
A85: 216022 | B85: 808108001002 | C85: =LEFT(B85,11) -> 80810800100 | D85: =RIGHT(B85,1) -> 2 | E85: CH DEUTZ BRUT CLASSIC 75CL | I85: =COUNTIF(#REF!,'Ref Unité VS Pack'!B85) -> #REF!
A86: 285416 | B86: 809940001001 | C86: =LEFT(B86,11) -> 80994000100 | D86: =RIGHT(B86,1) -> 1 | E86: CH FEUILLAT BRT RESV EXCL 75CL | F86: 1 | G86: 6 | H86: FALSE | I86: =COUNTIF(#REF!,'Ref Unité VS Pack'!B86) -> #REF!
A87: 215431 | B87: 809940001002 | C87: =LEFT(B87,11) -> 80994000100 | D87: =RIGHT(B87,1) -> 2 | E87: CH FEUILLAT BRT RESV EXCL 75CL | H87: FALSE | I87: =COUNTIF(#REF!,'Ref Unité VS Pack'!B87) -> #REF!
A88: 285530 | B88: 875882001001 | C88: =LEFT(B88,11) -> 87588200100 | D88: =RIGHT(B88,1) -> 1 | E88: CH FEUILLATE TRADITION BRT 75C | F88: 1 | G88: 6 | H88: FALSE | I88: =COUNTIF(#REF!,'Ref Unité VS Pack'!B88) -> #REF!
A89: 285531 | B89: 875882001002 | C89: =LEFT(B89,11) -> 87588200100 | D89: =RIGHT(B89,1) -> 2 | E89: CH FEUILLATE TRADITION BRT 75C | F89: 6 | G89: 6 | H89: FALSE | I89: =COUNTIF(#REF!,'Ref Unité VS Pack'!B89) -> #REF!
A90: 210572 | B90: 804855001001 | C90: =LEFT(B90,11) -> 80485500100 | D90: =RIGHT(B90,1) -> 1 | E90: CH GONET SULCOVA BDB GC 75CL | F90: 1 | G90: 6 | H90: FALSE | I90: =COUNTIF(#REF!,'Ref Unité VS Pack'!B90) -> #REF!
A91: 212696 | B91: 804855001002 | C91: =LEFT(B91,11) -> 80485500100 | D91: =RIGHT(B91,1) -> 2 | E91: CH GONET SULCOVA BDB GC 75CL | H91: FALSE | I91: =COUNTIF(#REF!,'Ref Unité VS Pack'!B91) -> #REF!
A92: 221714 | B92: 815589001002 | C92: =LEFT(B92,11) -> 81558900100 | D92: =RIGHT(B92,1) -> 2 | E92: CH GREMILLET BLC DE NOIR 75C | I92: =COUNTIF(#REF!,'Ref Unité VS Pack'!B92) -> #REF!
A93: 206660 | B93: 801190001001 | C93: =LEFT(B93,11) -> 80119000100 | D93: =RIGHT(B93,1) -> 1 | E93: CH L PERRIER LA CUVEE 75CL | F93: 1 | G93: 6 | H93: FALSE | I93: =COUNTIF(#REF!,'Ref Unité VS Pack'!B93) -> #REF!
A94: 212693 | B94: 801190001002 | C94: =LEFT(B94,11) -> 80119000100 | D94: =RIGHT(B94,1) -> 2 | E94: CH L PERRIER LA CUVEE 75CL | H94: FALSE | I94: =COUNTIF(#REF!,'Ref Unité VS Pack'!B94) -> #REF!
A95: 272653 | B95: 863583001002 | C95: =LEFT(B95,11) -> 86358300100 | D95: =RIGHT(B95,1) -> 2 | E95: CH MOET&CHANDON IMPERIAL 75CL | H95: FALSE | I95: =COUNTIF(#REF!,'Ref Unité VS Pack'!B95) -> #REF!
A96: 215201 | B96: 809034001001 | C96: =LEFT(B96,11) -> 80903400100 | D96: =RIGHT(B96,1) -> 1 | E96: CH NFEUILLATTE RSE R EXCL 75CL | F96: 1 | G96: 6 | H96: FALSE | I96: =COUNTIF(#REF!,'Ref Unité VS Pack'!B96) -> #REF!
A97: 215202 | B97: 809034001002 | C97: =LEFT(B97,11) -> 80903400100 | D97: =RIGHT(B97,1) -> 2 | E97: CH NFEUILLATTE RSE R EXCL 75CL | H97: FALSE | I97: =COUNTIF(#REF!,'Ref Unité VS Pack'!B97) -> #REF!
A98: 216763 | B98: 810517001001 | C98: =LEFT(B98,11) -> 81051700100 | D98: =RIGHT(B98,1) -> 1 | E98: CH POMMERY BRUT ROYAL 75CL | F98: 1 | G98: 6 | H98: FALSE | I98: =COUNTIF(#REF!,'Ref Unité VS Pack'!B98) -> #REF!
A99: 216764 | B99: 810517001002 | C99: =LEFT(B99,11) -> 81051700100 | D99: =RIGHT(B99,1) -> 2 | E99: CH POMMERY BRUT ROYAL 75CL | H99: FALSE | I99: =COUNTIF(#REF!,'Ref Unité VS Pack'!B99) -> #REF!
A100: 213193 | B100: 807495001002 | C100: =LEFT(B100,11) -> 80749500100 | D100: =RIGHT(B100,1) -> 2 | E100: CH TAITTINGER BRUT 75CL | I100: =COUNTIF(#REF!,'Ref Unité VS Pack'!B100) -> #REF!
...
